auth0_ai_llamaindex/FGARetriever.py
auth0_ai_llamaindex/__init__.py
auth0_ai_llamaindex/async_authorization/__init__.py
auth0_ai_llamaindex/async_authorization/async_authorizer.py
auth0_ai_llamaindex/auth0_ai.py
auth0_ai_llamaindex/context.py
auth0_ai_llamaindex/fga/__init__.py
auth0_ai_llamaindex/token_vault/__init__.py
auth0_ai_llamaindex/token_vault/token_vault_authorizer.py
auth0_ai_llamaindex/utils/tool_wrapper.py
auth0_ai_llamaindex-1.0.1.dist-info/LICENSE
auth0_ai_llamaindex-1.0.1.dist-info/METADATA
auth0_ai_llamaindex-1.0.1.dist-info/WHEEL
auth0_ai_llamaindex-1.0.1.dist-info/RECORD
